.editorconfig
.gitignore
.travis.yml
AUTHORS.rst
CONTRIBUTING.rst
HISTORY.rst
LICENSE
MANIFEST.in
Makefile
README.md
requirements_dev.txt
setup.cfg
setup.py
tox.ini
.github/ISSUE_TEMPLATE.md
assets/pyturkce-logo.png
docs/Makefile
docs/authors.rst
docs/conf.py
docs/contributing.rst
docs/history.rst
docs/index.rst
docs/installation.rst
docs/make.bat
docs/readme.rst
docs/usage.rst
pyturkce/__init__.py
pyturkce/cli.py
pyturkce/crypt.py
pyturkce/pyturkce.py
pyturkce/utils.py
pyturkce.egg-info/PKG-INFO
pyturkce.egg-info/SOURCES.txt
pyturkce.egg-info/dependency_links.txt
pyturkce.egg-info/entry_points.txt
pyturkce.egg-info/not-zip-safe
pyturkce.egg-info/top_level.txt
tests/__init__.py
tests/test_pyturkce.py