Metadata-Version: 2.1
Name: pyturkce
Version: 0.1.3
Summary: Python package for Turkish Language.
Home-page: https://github.com/cobanov/pyturkce
Author: Mert Cobanov
Author-email: mertcobanov@gmail.com
License: MIT license
Keywords: pyturkce
Platform: UNKNOWN
Classifier: Development Status :: 2 - Pre-Alpha
Classifier: Intended Audience :: Developers
Classifier: License :: OSI Approved :: MIT License
Classifier: Natural Language :: English
Classifier: Programming Language :: Python :: 3
Classifier: Programming Language :: Python :: 3.6
Classifier: Programming Language :: Python :: 3.7
Classifier: Programming Language :: Python :: 3.8
Requires-Python: >=3.6
